{
  "annotations": {
    "list": [
      {
        "builtIn": 1,
        "datasource": { "type": "grafana", "uid": "-- Grafana --" },
        "enable": true,
        "hide": true,
        "iconColor": "rgba(0, 211, 255, 1)",
        "name": "Annotations & Alerts",
        "type": "dashboard"
      }
    ]
  },
  "description": "ACM Equipment Behavior Dashboard - Health scores, anomaly detection, RUL predictions, and episode diagnostics",
  "editable": true,
  "fiscalYearStartMonth": 0,
  "graphTooltip": 1,
  "id": null,
  "uid": "acm-behavior",
  "title": "ACM Behavior",
  "links": [],
  "panels": [
    {
      "collapsed": false,
      "gridPos": { "h": 1, "w": 24, "x": 0, "y": 0 },
      "id": 100,
      "panels": [],
      "title": "HEALTH OVERVIEW",
      "type": "row"
    },
    {
      "datasource": { "type": "mssql", "uid": "${datasource}" },
      "description": "Current health score (0-100%)",
      "fieldConfig": {
        "defaults": {
          "color": { "mode": "thresholds" },
          "mappings": [],
          "max": 100,
          "min": 0,
          "thresholds": {
            "mode": "absolute",
            "steps": [
              { "color": "red", "value": null },
              { "color": "orange", "value": 50 },
              { "color": "yellow", "value": 70 },
              { "color": "green", "value": 85 }
            ]
          },
          "unit": "percent"
        },
        "overrides": []
      },
      "gridPos": { "h": 6, "w": 4, "x": 0, "y": 1 },
      "id": 1,
      "options": {
        "minVizHeight": 75,
        "minVizWidth": 75,
        "orientation": "auto",
        "reduceOptions": { "calcs": ["lastNotNull"], "fields": "", "values": false },
        "showThresholdLabels": false,
        "showThresholdMarkers": true,
        "sizing": "auto"
      },
      "pluginVersion": "12.0.0",
      "targets": [
        {
          "datasource": { "type": "mssql", "uid": "${datasource}" },
          "editorMode": "code",
          "format": "table",
          "rawQuery": true,
          "rawSql": "SELECT TOP 1 Health\nFROM ACM_HealthTimeline\nWHERE EquipID = $equipment\nORDER BY Timestamp DESC",
          "refId": "A"
        }
      ],
      "title": "CURRENT HEALTH",
      "type": "gauge"
    },
    {
      "datasource": { "type": "mssql", "uid": "${datasource}" },
      "description": "Current health zone classification",
      "fieldConfig": {
        "defaults": {
          "color": { "mode": "thresholds" },
          "mappings": [
            { "options": { "GOOD": { "color": "green", "index": 0, "text": "GOOD" } }, "type": "value" },
            { "options": { "WATCH": { "color": "yellow", "index": 1, "text": "WATCH" } }, "type": "value" },
            { "options": { "ALERT": { "color": "orange", "index": 2, "text": "ALERT" } }, "type": "value" },
            { "options": { "CRITICAL": { "color": "red", "index": 3, "text": "CRITICAL" } }, "type": "value" }
          ],
          "thresholds": { "mode": "absolute", "steps": [{ "color": "blue", "value": null }] }
        },
        "overrides": []
      },
      "gridPos": { "h": 3, "w": 4, "x": 4, "y": 1 },
      "id": 2,
      "options": {
        "colorMode": "background",
        "graphMode": "none",
        "justifyMode": "center",
        "orientation": "horizontal",
        "reduceOptions": { "calcs": ["lastNotNull"], "fields": "", "values": false },
        "showPercentChange": false,
        "textMode": "value",
        "wideLayout": true
      },
      "pluginVersion": "12.0.0",
      "targets": [
        {
          "datasource": { "type": "mssql", "uid": "${datasource}" },
          "editorMode": "code",
          "format": "table",
          "rawQuery": true,
          "rawSql": "SELECT TOP 1 HealthZone\nFROM ACM_HealthTimeline\nWHERE EquipID = $equipment\nORDER BY Timestamp DESC",
          "refId": "A"
        }
      ],
      "title": "HEALTH ZONE",
      "type": "stat"
    },
    {
      "datasource": { "type": "mssql", "uid": "${datasource}" },
      "description": "Current fused anomaly score",
      "fieldConfig": {
        "defaults": {
          "color": { "mode": "thresholds" },
          "mappings": [],
          "max": 10,
          "min": 0,
          "thresholds": {
            "mode": "absolute",
            "steps": [
              { "color": "green", "value": null },
              { "color": "yellow", "value": 3 },
              { "color": "orange", "value": 5 },
              { "color": "red", "value": 7 }
            ]
          },
          "unit": "none"
        },
        "overrides": []
      },
      "gridPos": { "h": 3, "w": 4, "x": 4, "y": 4 },
      "id": 3,
      "options": {
        "colorMode": "background",
        "graphMode": "area",
        "justifyMode": "center",
        "orientation": "horizontal",
        "reduceOptions": { "calcs": ["lastNotNull"], "fields": "", "values": false },
        "showPercentChange": false,
        "textMode": "value_and_name",
        "wideLayout": true
      },
      "pluginVersion": "12.0.0",
      "targets": [
        {
          "datasource": { "type": "mssql", "uid": "${datasource}" },
          "editorMode": "code",
          "format": "table",
          "rawQuery": true,
          "rawSql": "SELECT TOP 1 FusedZ AS 'Fused Z'\nFROM ACM_HealthTimeline\nWHERE EquipID = $equipment\nORDER BY Timestamp DESC",
          "refId": "A"
        }
      ],
      "title": "FUSED Z-SCORE",
      "type": "stat"
    },
    {
      "datasource": { "type": "mssql", "uid": "${datasource}" },
      "description": "Remaining Useful Life prediction",
      "fieldConfig": {
        "defaults": {
          "color": { "mode": "thresholds" },
          "mappings": [],
          "thresholds": {
            "mode": "absolute",
            "steps": [
              { "color": "red", "value": null },
              { "color": "orange", "value": 24 },
              { "color": "yellow", "value": 72 },
              { "color": "green", "value": 168 }
            ]
          },
          "unit": "h"
        },
        "overrides": []
      },
      "gridPos": { "h": 6, "w": 4, "x": 8, "y": 1 },
      "id": 4,
      "options": {
        "colorMode": "background_solid",
        "graphMode": "none",
        "justifyMode": "center",
        "orientation": "horizontal",
        "reduceOptions": { "calcs": ["lastNotNull"], "fields": "", "values": false },
        "showPercentChange": false,
        "textMode": "value_and_name",
        "wideLayout": true
      },
      "pluginVersion": "12.0.0",
      "targets": [
        {
          "datasource": { "type": "mssql", "uid": "${datasource}" },
          "editorMode": "code",
          "format": "table",
          "rawQuery": true,
          "rawSql": "SELECT TOP 1 ROUND(RUL_Hours, 1) AS 'RUL (Hours)'\nFROM ACM_RUL\nWHERE EquipID = $equipment\n  AND (P10_LowerBound IS NOT NULL OR P50_Median IS NOT NULL)\nORDER BY CreatedAt DESC",
          "refId": "A"
        }
      ],
      "title": "RUL PREDICTION",
      "type": "stat"
    },
    {
      "datasource": { "type": "mssql", "uid": "${datasource}" },
      "description": "RUL confidence bounds (P10/P50/P90)",
      "fieldConfig": {
        "defaults": {
          "color": { "mode": "thresholds" },
          "custom": {
            "align": "center",
            "cellOptions": { "type": "auto" },
            "filterable": false,
            "inspect": false
          },
          "thresholds": { "mode": "absolute", "steps": [{ "color": "text", "value": null }] }
        },
        "overrides": []
      },
      "gridPos": { "h": 6, "w": 4, "x": 12, "y": 1 },
      "id": 5,
      "options": {
        "cellHeight": "sm",
        "footer": { "countRows": false, "fields": "", "reducer": ["sum"], "show": false },
        "showHeader": true
      },
      "pluginVersion": "12.0.0",
      "targets": [
        {
          "datasource": { "type": "mssql", "uid": "${datasource}" },
          "editorMode": "code",
          "format": "table",
          "rawQuery": true,
          "rawSql": "SELECT TOP 1\n  ROUND(P10_LowerBound, 1) AS 'P10 (h)',\n  ROUND(P50_Median, 1) AS 'P50 (h)',\n  ROUND(P90_UpperBound, 1) AS 'P90 (h)',\n  ROUND(Confidence, 2) AS 'Conf'\nFROM ACM_RUL\nWHERE EquipID = $equipment\n  AND (P10_LowerBound IS NOT NULL OR P50_Median IS NOT NULL)\nORDER BY CreatedAt DESC",
          "refId": "A"
        }
      ],
      "title": "RUL BOUNDS",
      "type": "table"
    },
    {
      "datasource": { "type": "mssql", "uid": "${datasource}" },
      "description": "Active anomaly episodes",
      "fieldConfig": {
        "defaults": {
          "color": { "mode": "thresholds" },
          "mappings": [],
          "thresholds": {
            "mode": "absolute",
            "steps": [
              { "color": "green", "value": null },
              { "color": "yellow", "value": 1 },
              { "color": "orange", "value": 3 },
              { "color": "red", "value": 5 }
            ]
          }
        },
        "overrides": []
      },
      "gridPos": { "h": 3, "w": 4, "x": 16, "y": 1 },
      "id": 6,
      "options": {
        "colorMode": "background",
        "graphMode": "none",
        "justifyMode": "center",
        "orientation": "horizontal",
        "reduceOptions": { "calcs": ["lastNotNull"], "fields": "", "values": false },
        "showPercentChange": false,
        "textMode": "value_and_name",
        "wideLayout": true
      },
      "pluginVersion": "12.0.0",
      "targets": [
        {
          "datasource": { "type": "mssql", "uid": "${datasource}" },
          "editorMode": "code",
          "format": "table",
          "rawQuery": true,
          "rawSql": "SELECT COUNT(*) AS 'Active Episodes'\nFROM ACM_Episodes\nWHERE EquipID = $equipment\n  AND EndTime IS NULL",
          "refId": "A"
        }
      ],
      "title": "ACTIVE EPISODES",
      "type": "stat"
    },
    {
      "datasource": { "type": "mssql", "uid": "${datasource}" },
      "description": "Total episodes in time range",
      "fieldConfig": {
        "defaults": {
          "color": { "mode": "thresholds" },
          "mappings": [],
          "thresholds": { "mode": "absolute", "steps": [{ "color": "blue", "value": null }] }
        },
        "overrides": []
      },
      "gridPos": { "h": 3, "w": 4, "x": 16, "y": 4 },
      "id": 7,
      "options": {
        "colorMode": "background",
        "graphMode": "none",
        "justifyMode": "center",
        "orientation": "horizontal",
        "reduceOptions": { "calcs": ["lastNotNull"], "fields": "", "values": false },
        "showPercentChange": false,
        "textMode": "value_and_name",
        "wideLayout": true
      },
      "pluginVersion": "12.0.0",
      "targets": [
        {
          "datasource": { "type": "mssql", "uid": "${datasource}" },
          "editorMode": "code",
          "format": "table",
          "rawQuery": true,
          "rawSql": "SELECT COUNT(*) AS 'Total Episodes'\nFROM ACM_Episodes\nWHERE EquipID = $equipment\n  AND StartTime BETWEEN $__timeFrom() AND $__timeTo()",
          "refId": "A"
        }
      ],
      "title": "EPISODES (RANGE)",
      "type": "stat"
    },
    {
      "datasource": { "type": "mssql", "uid": "${datasource}" },
      "description": "Current operating regime",
      "fieldConfig": {
        "defaults": {
          "color": { "mode": "thresholds" },
          "mappings": [],
          "thresholds": { "mode": "absolute", "steps": [{ "color": "purple", "value": null }] }
        },
        "overrides": []
      },
      "gridPos": { "h": 3, "w": 4, "x": 20, "y": 1 },
      "id": 8,
      "options": {
        "colorMode": "background",
        "graphMode": "none",
        "justifyMode": "center",
        "orientation": "horizontal",
        "reduceOptions": { "calcs": ["lastNotNull"], "fields": "", "values": false },
        "showPercentChange": false,
        "textMode": "value_and_name",
        "wideLayout": true
      },
      "pluginVersion": "12.0.0",
      "targets": [
        {
          "datasource": { "type": "mssql", "uid": "${datasource}" },
          "editorMode": "code",
          "format": "table",
          "rawQuery": true,
          "rawSql": "SELECT TOP 1 RegimeLabel AS 'Regime'\nFROM ACM_RegimeTimeline\nWHERE EquipID = $equipment\nORDER BY Timestamp DESC",
          "refId": "A"
        }
      ],
      "title": "CURRENT REGIME",
      "type": "stat"
    },
    {
      "datasource": { "type": "mssql", "uid": "${datasource}" },
      "description": "Total regimes detected",
      "fieldConfig": {
        "defaults": {
          "color": { "mode": "thresholds" },
          "mappings": [],
          "thresholds": { "mode": "absolute", "steps": [{ "color": "purple", "value": null }] }
        },
        "overrides": []
      },
      "gridPos": { "h": 3, "w": 4, "x": 20, "y": 4 },
      "id": 9,
      "options": {
        "colorMode": "background",
        "graphMode": "none",
        "justifyMode": "center",
        "orientation": "horizontal",
        "reduceOptions": { "calcs": ["lastNotNull"], "fields": "", "values": false },
        "showPercentChange": false,
        "textMode": "value_and_name",
        "wideLayout": true
      },
      "pluginVersion": "12.0.0",
      "targets": [
        {
          "datasource": { "type": "mssql", "uid": "${datasource}" },
          "editorMode": "code",
          "format": "table",
          "rawQuery": true,
          "rawSql": "SELECT COUNT(DISTINCT RegimeLabel) AS 'Regimes'\nFROM ACM_RegimeTimeline\nWHERE EquipID = $equipment",
          "refId": "A"
        }
      ],
      "title": "TOTAL REGIMES",
      "type": "stat"
    },
    {
      "collapsed": false,
      "gridPos": { "h": 1, "w": 24, "x": 0, "y": 7 },
      "id": 101,
      "panels": [],
      "title": "HEALTH TIMELINE",
      "type": "row"
    },
    {
      "datasource": { "type": "mssql", "uid": "${datasource}" },
      "description": "Health score over time with zone coloring",
      "fieldConfig": {
        "defaults": {
          "color": { "mode": "thresholds" },
          "custom": {
            "axisBorderShow": false,
            "axisCenteredZero": false,
            "axisColorMode": "text",
            "axisLabel": "",
            "axisPlacement": "auto",
            "barAlignment": 0,
            "barWidthFactor": 0.6,
            "drawStyle": "line",
            "fillOpacity": 20,
            "gradientMode": "scheme",
            "hideFrom": { "legend": false, "tooltip": false, "viz": false },
            "insertNulls": false,
            "lineInterpolation": "smooth",
            "lineWidth": 2,
            "pointSize": 5,
            "scaleDistribution": { "type": "linear" },
            "showPoints": "never",
            "spanNulls": 3600000,
            "stacking": { "group": "A", "mode": "none" },
            "thresholdsStyle": { "mode": "area" }
          },
          "mappings": [],
          "max": 100,
          "min": 0,
          "thresholds": {
            "mode": "absolute",
            "steps": [
              { "color": "red", "value": null },
              { "color": "orange", "value": 50 },
              { "color": "yellow", "value": 70 },
              { "color": "green", "value": 85 }
            ]
          },
          "unit": "percent"
        },
        "overrides": []
      },
      "gridPos": { "h": 8, "w": 24, "x": 0, "y": 8 },
      "id": 10,
      "options": {
        "legend": { "calcs": ["mean", "min", "max", "lastNotNull"], "displayMode": "table", "placement": "bottom", "showLegend": true },
        "tooltip": { "mode": "multi", "sort": "desc" }
      },
      "pluginVersion": "12.0.0",
      "targets": [
        {
          "datasource": { "type": "mssql", "uid": "${datasource}" },
          "editorMode": "code",
          "format": "time_series",
          "rawQuery": true,
          "rawSql": "SELECT\n  Timestamp AS time,\n  Health AS 'Health %'\nFROM ACM_HealthTimeline\nWHERE EquipID = $equipment\n  AND Timestamp BETWEEN $__timeFrom() AND $__timeTo()\nORDER BY Timestamp ASC",
          "refId": "A"
        }
      ],
      "title": "Health Score Timeline",
      "type": "timeseries"
    },
    {
      "collapsed": false,
      "gridPos": { "h": 1, "w": 24, "x": 0, "y": 16 },
      "id": 102,
      "panels": [],
      "title": "DETECTOR SCORES",
      "type": "row"
    },
    {
      "datasource": { "type": "mssql", "uid": "${datasource}" },
      "description": "Individual detector Z-scores over time",
      "fieldConfig": {
        "defaults": {
          "color": { "mode": "palette-classic" },
          "custom": {
            "axisBorderShow": false,
            "axisCenteredZero": false,
            "axisColorMode": "text",
            "axisLabel": "Z-Score",
            "axisPlacement": "auto",
            "barAlignment": 0,
            "barWidthFactor": 0.6,
            "drawStyle": "line",
            "fillOpacity": 10,
            "gradientMode": "none",
            "hideFrom": { "legend": false, "tooltip": false, "viz": false },
            "insertNulls": false,
            "lineInterpolation": "smooth",
            "lineWidth": 1,
            "pointSize": 5,
            "scaleDistribution": { "type": "linear" },
            "showPoints": "never",
            "spanNulls": 3600000,
            "stacking": { "group": "A", "mode": "none" },
            "thresholdsStyle": { "mode": "line" }
          },
          "mappings": [],
          "max": 10,
          "min": 0,
          "thresholds": {
            "mode": "absolute",
            "steps": [
              { "color": "green", "value": null },
              { "color": "red", "value": 3 }
            ]
          },
          "unit": "none"
        },
        "overrides": []
      },
      "gridPos": { "h": 8, "w": 24, "x": 0, "y": 17 },
      "id": 11,
      "options": {
        "legend": { "calcs": ["mean", "max", "lastNotNull"], "displayMode": "table", "placement": "right", "showLegend": true },
        "tooltip": { "mode": "multi", "sort": "desc" }
      },
      "pluginVersion": "12.0.0",
      "targets": [
        {
          "datasource": { "type": "mssql", "uid": "${datasource}" },
          "editorMode": "code",
          "format": "time_series",
          "rawQuery": true,
          "rawSql": "SELECT\n  Timestamp AS time,\n  ar1_z AS 'AR1',\n  pca_spe_z AS 'PCA-SPE',\n  pca_t2_z AS 'PCA-T2',\n  iforest_z AS 'IForest',\n  gmm_z AS 'GMM',\n  omr_z AS 'OMR',\n  fused_z AS 'Fused'\nFROM ACM_Scores_Wide\nWHERE EquipID = $equipment\n  AND Timestamp BETWEEN $__timeFrom() AND $__timeTo()\nORDER BY Timestamp ASC",
          "refId": "A"
        }
      ],
      "title": "Detector Z-Scores",
      "type": "timeseries"
    },
    {
      "collapsed": false,
      "gridPos": { "h": 1, "w": 24, "x": 0, "y": 25 },
      "id": 103,
      "panels": [],
      "title": "ANOMALY EVENTS & EPISODES",
      "type": "row"
    },
    {
      "datasource": { "type": "mssql", "uid": "${datasource}" },
      "description": "Anomaly events by hour",
      "fieldConfig": {
        "defaults": {
          "color": { "mode": "palette-classic" },
          "custom": {
            "axisBorderShow": false,
            "axisCenteredZero": false,
            "axisColorMode": "text",
            "axisLabel": "",
            "axisPlacement": "auto",
            "barAlignment": 0,
            "barWidthFactor": 0.6,
            "drawStyle": "bars",
            "fillOpacity": 80,
            "gradientMode": "hue",
            "hideFrom": { "legend": false, "tooltip": false, "viz": false },
            "insertNulls": false,
            "lineInterpolation": "linear",
            "lineWidth": 1,
            "pointSize": 5,
            "scaleDistribution": { "type": "linear" },
            "showPoints": "never",
            "spanNulls": false,
            "stacking": { "group": "A", "mode": "none" },
            "thresholdsStyle": { "mode": "off" }
          },
          "mappings": [],
          "thresholds": { "mode": "absolute", "steps": [{ "color": "green", "value": null }] },
          "unit": "none"
        },
        "overrides": []
      },
      "gridPos": { "h": 6, "w": 12, "x": 0, "y": 26 },
      "id": 12,
      "options": {
        "legend": { "calcs": [], "displayMode": "list", "placement": "bottom", "showLegend": true },
        "tooltip": { "mode": "single", "sort": "none" }
      },
      "pluginVersion": "12.0.0",
      "targets": [
        {
          "datasource": { "type": "mssql", "uid": "${datasource}" },
          "editorMode": "code",
          "format": "time_series",
          "rawQuery": true,
          "rawSql": "SELECT\n  DATEADD(HOUR, DATEDIFF(HOUR, 0, StartTime), 0) AS time,\n  COUNT(*) AS 'Events'\nFROM ACM_Anomaly_Events\nWHERE EquipID = $equipment\n  AND StartTime BETWEEN $__timeFrom() AND $__timeTo()\nGROUP BY DATEADD(HOUR, DATEDIFF(HOUR, 0, StartTime), 0)\nORDER BY time ASC",
          "refId": "A"
        }
      ],
      "title": "Anomaly Events (Hourly)",
      "type": "timeseries"
    },
    {
      "datasource": { "type": "mssql", "uid": "${datasource}" },
      "description": "Recent episodes with diagnostics",
      "fieldConfig": {
        "defaults": {
          "color": { "mode": "thresholds" },
          "custom": {
            "align": "auto",
            "cellOptions": { "type": "auto" },
            "filterable": true,
            "inspect": false
          },
          "thresholds": { "mode": "absolute", "steps": [{ "color": "text", "value": null }] }
        },
        "overrides": [
          {
            "matcher": { "id": "byName", "options": "Duration (h)" },
            "properties": [
              { "id": "custom.cellOptions", "value": { "mode": "gradient", "type": "gauge", "valueDisplayMode": "color" } },
              { "id": "color", "value": { "mode": "continuous-BlYlRd" } },
              { "id": "max", "value": 24 }
            ]
          },
          {
            "matcher": { "id": "byName", "options": "MaxZ" },
            "properties": [
              { "id": "color", "value": { "mode": "thresholds" } },
              { "id": "thresholds", "value": { "mode": "absolute", "steps": [{ "color": "green", "value": null }, { "color": "yellow", "value": 3 }, { "color": "red", "value": 5 }] } },
              { "id": "custom.cellOptions", "value": { "mode": "gradient", "type": "color-background" } }
            ]
          }
        ]
      },
      "gridPos": { "h": 6, "w": 12, "x": 12, "y": 26 },
      "id": 13,
      "options": {
        "cellHeight": "sm",
        "footer": { "countRows": false, "fields": "", "reducer": ["sum"], "show": false },
        "showHeader": true,
        "sortBy": [{ "desc": true, "displayName": "StartTimeStr" }]
      },
      "pluginVersion": "12.0.0",
      "targets": [
        {
          "datasource": { "type": "mssql", "uid": "${datasource}" },
          "editorMode": "code",
          "format": "table",
          "rawQuery": true,
          "rawSql": "SELECT TOP 20\n  FORMAT(ed.start_ts, 'yyyy-MM-dd HH:mm') AS 'StartTimeStr',\n  ROUND(ed.duration_h, 2) AS 'Duration (h)',\n  ROUND(ed.max_z, 2) AS 'MaxZ',\n  ed.dominant_detector AS 'Detector',\n  ed.dominant_regime AS 'Regime',\n  COALESCE(ed.sensor_summary, '-') AS 'Top Sensors'\nFROM ACM_EpisodeDiagnostics ed\nWHERE ed.EquipID = $equipment\n  AND ed.start_ts BETWEEN $__timeFrom() AND $__timeTo()\nORDER BY ed.start_ts DESC",
          "refId": "A"
        }
      ],
      "title": "Recent Episodes",
      "type": "table"
    },
    {
      "collapsed": false,
      "gridPos": { "h": 1, "w": 24, "x": 0, "y": 32 },
      "id": 104,
      "panels": [],
      "title": "REGIME & DRIFT",
      "type": "row"
    },
    {
      "datasource": { "type": "mssql", "uid": "${datasource}" },
      "description": "Operating regime over time",
      "fieldConfig": {
        "defaults": {
          "color": { "mode": "palette-classic" },
          "custom": {
            "axisBorderShow": false,
            "axisCenteredZero": false,
            "axisColorMode": "text",
            "axisLabel": "",
            "axisPlacement": "auto",
            "barAlignment": 0,
            "barWidthFactor": 0.6,
            "drawStyle": "line",
            "fillOpacity": 50,
            "gradientMode": "scheme",
            "hideFrom": { "legend": false, "tooltip": false, "viz": false },
            "insertNulls": false,
            "lineInterpolation": "stepAfter",
            "lineWidth": 1,
            "pointSize": 5,
            "scaleDistribution": { "type": "linear" },
            "showPoints": "never",
            "spanNulls": 3600000,
            "stacking": { "group": "A", "mode": "none" },
            "thresholdsStyle": { "mode": "off" }
          },
          "mappings": [],
          "thresholds": { "mode": "absolute", "steps": [{ "color": "green", "value": null }] }
        },
        "overrides": []
      },
      "gridPos": { "h": 6, "w": 12, "x": 0, "y": 33 },
      "id": 14,
      "options": {
        "legend": { "calcs": [], "displayMode": "list", "placement": "bottom", "showLegend": true },
        "tooltip": { "mode": "single", "sort": "none" }
      },
      "pluginVersion": "12.0.0",
      "targets": [
        {
          "datasource": { "type": "mssql", "uid": "${datasource}" },
          "editorMode": "code",
          "format": "time_series",
          "rawQuery": true,
          "rawSql": "SELECT\n  Timestamp AS time,\n  RegimeID AS 'Regime ID'\nFROM ACM_RegimeTimeline\nWHERE EquipID = $equipment\n  AND Timestamp BETWEEN $__timeFrom() AND $__timeTo()\nORDER BY Timestamp ASC",
          "refId": "A"
        }
      ],
      "title": "Regime Timeline",
      "type": "timeseries"
    },
    {
      "datasource": { "type": "mssql", "uid": "${datasource}" },
      "description": "Regime occupancy distribution",
      "fieldConfig": {
        "defaults": {
          "color": { "mode": "palette-classic" },
          "custom": { "hideFrom": { "legend": false, "tooltip": false, "viz": false } },
          "mappings": [],
          "unit": "percentunit"
        },
        "overrides": []
      },
      "gridPos": { "h": 6, "w": 6, "x": 12, "y": 33 },
      "id": 15,
      "options": {
        "displayLabels": ["name", "percent"],
        "legend": { "displayMode": "list", "placement": "right", "showLegend": true },
        "pieType": "pie",
        "reduceOptions": { "calcs": ["lastNotNull"], "fields": "", "values": false },
        "tooltip": { "mode": "single", "sort": "none" }
      },
      "pluginVersion": "12.0.0",
      "targets": [
        {
          "datasource": { "type": "mssql", "uid": "${datasource}" },
          "editorMode": "code",
          "format": "table",
          "rawQuery": true,
          "rawSql": "SELECT\n  RegimeLabel,\n  Occupancy\nFROM ACM_RegimeOccupancy\nWHERE EquipID = $equipment\n  AND RunID = (\n    SELECT TOP 1 RunID FROM ACM_Runs\n    WHERE EquipID = $equipment\n    ORDER BY CreatedAt DESC\n  )",
          "refId": "A"
        }
      ],
      "title": "Regime Occupancy",
      "type": "piechart"
    },
    {
      "datasource": { "type": "mssql", "uid": "${datasource}" },
      "description": "Concept drift score over time",
      "fieldConfig": {
        "defaults": {
          "color": { "mode": "thresholds" },
          "custom": {
            "axisBorderShow": false,
            "axisCenteredZero": false,
            "axisColorMode": "text",
            "axisLabel": "",
            "axisPlacement": "auto",
            "barAlignment": 0,
            "barWidthFactor": 0.6,
            "drawStyle": "line",
            "fillOpacity": 20,
            "gradientMode": "scheme",
            "hideFrom": { "legend": false, "tooltip": false, "viz": false },
            "insertNulls": false,
            "lineInterpolation": "smooth",
            "lineWidth": 1,
            "pointSize": 5,
            "scaleDistribution": { "type": "linear" },
            "showPoints": "never",
            "spanNulls": 3600000,
            "stacking": { "group": "A", "mode": "none" },
            "thresholdsStyle": { "mode": "line" }
          },
          "mappings": [],
          "max": 1,
          "min": 0,
          "thresholds": {
            "mode": "absolute",
            "steps": [
              { "color": "green", "value": null },
              { "color": "yellow", "value": 0.3 },
              { "color": "red", "value": 0.6 }
            ]
          }
        },
        "overrides": []
      },
      "gridPos": { "h": 6, "w": 6, "x": 18, "y": 33 },
      "id": 16,
      "options": {
        "legend": { "calcs": [], "displayMode": "list", "placement": "bottom", "showLegend": false },
        "tooltip": { "mode": "single", "sort": "none" }
      },
      "pluginVersion": "12.0.0",
      "targets": [
        {
          "datasource": { "type": "mssql", "uid": "${datasource}" },
          "editorMode": "code",
          "format": "time_series",
          "rawQuery": true,
          "rawSql": "SELECT\n  Timestamp AS time,\n  DriftScore AS 'Drift'\nFROM ACM_DriftSeries\nWHERE EquipID = $equipment\n  AND Timestamp BETWEEN $__timeFrom() AND $__timeTo()\nORDER BY Timestamp ASC",
          "refId": "A"
        }
      ],
      "title": "Drift Score",
      "type": "timeseries"
    },
    {
      "collapsed": false,
      "gridPos": { "h": 1, "w": 24, "x": 0, "y": 39 },
      "id": 105,
      "panels": [],
      "title": "SENSOR CONTRIBUTIONS",
      "type": "row"
    },
    {
      "datasource": { "type": "mssql", "uid": "${datasource}" },
      "description": "Top sensor contributors to anomalies",
      "fieldConfig": {
        "defaults": {
          "color": { "mode": "palette-classic" },
          "custom": {
            "axisBorderShow": false,
            "axisCenteredZero": false,
            "axisColorMode": "text",
            "axisLabel": "",
            "axisPlacement": "auto",
            "barAlignment": 0,
            "barWidthFactor": 0.6,
            "drawStyle": "bars",
            "fillOpacity": 80,
            "gradientMode": "hue",
            "hideFrom": { "legend": false, "tooltip": false, "viz": false },
            "insertNulls": false,
            "lineInterpolation": "linear",
            "lineWidth": 1,
            "pointSize": 5,
            "scaleDistribution": { "type": "linear" },
            "showPoints": "never",
            "spanNulls": false,
            "stacking": { "group": "A", "mode": "normal" },
            "thresholdsStyle": { "mode": "off" }
          },
          "mappings": [],
          "thresholds": { "mode": "absolute", "steps": [{ "color": "green", "value": null }] }
        },
        "overrides": []
      },
      "gridPos": { "h": 8, "w": 12, "x": 0, "y": 40 },
      "id": 17,
      "options": {
        "legend": { "calcs": [], "displayMode": "list", "placement": "bottom", "showLegend": true },
        "tooltip": { "mode": "multi", "sort": "desc" }
      },
      "pluginVersion": "12.0.0",
      "targets": [
        {
          "datasource": { "type": "mssql", "uid": "${datasource}" },
          "editorMode": "code",
          "format": "time_series",
          "rawQuery": true,
          "rawSql": "SELECT\n  Timestamp AS time,\n  SensorName AS metric,\n  Contribution AS value\nFROM ACM_ContributionTimeline\nWHERE EquipID = $equipment\n  AND Timestamp BETWEEN $__timeFrom() AND $__timeTo()\n  AND SensorName IN (\n    SELECT TOP 5 SensorName\n    FROM ACM_ContributionCurrent\n    WHERE EquipID = $equipment\n    ORDER BY Contribution DESC\n  )\nORDER BY Timestamp ASC",
          "refId": "A"
        }
      ],
      "title": "Top Sensor Contributions",
      "type": "timeseries"
    },
    {
      "datasource": { "type": "mssql", "uid": "${datasource}" },
      "description": "Current sensor contributions ranked",
      "fieldConfig": {
        "defaults": {
          "color": { "mode": "continuous-BlYlRd" },
          "custom": {
            "axisBorderShow": false,
            "axisCenteredZero": false,
            "axisColorMode": "text",
            "axisLabel": "",
            "axisPlacement": "auto",
            "barAlignment": 0,
            "barWidthFactor": 0.6,
            "drawStyle": "bars",
            "fillOpacity": 80,
            "gradientMode": "scheme",
            "hideFrom": { "legend": false, "tooltip": false, "viz": false },
            "insertNulls": false,
            "lineInterpolation": "linear",
            "lineWidth": 1,
            "pointSize": 5,
            "scaleDistribution": { "type": "linear" },
            "showPoints": "never",
            "spanNulls": false,
            "stacking": { "group": "A", "mode": "none" },
            "thresholdsStyle": { "mode": "off" }
          },
          "mappings": [],
          "thresholds": { "mode": "absolute", "steps": [{ "color": "green", "value": null }] }
        },
        "overrides": []
      },
      "gridPos": { "h": 8, "w": 12, "x": 12, "y": 40 },
      "id": 18,
      "options": {
        "legend": { "calcs": [], "displayMode": "hidden", "placement": "bottom", "showLegend": false },
        "orientation": "horizontal",
        "tooltip": { "mode": "single", "sort": "none" },
        "xField": "SensorName"
      },
      "pluginVersion": "12.0.0",
      "targets": [
        {
          "datasource": { "type": "mssql", "uid": "${datasource}" },
          "editorMode": "code",
          "format": "table",
          "rawQuery": true,
          "rawSql": "SELECT TOP 10\n  SensorName,\n  ROUND(Contribution, 3) AS Contribution\nFROM ACM_ContributionCurrent\nWHERE EquipID = $equipment\nORDER BY Contribution DESC",
          "refId": "A"
        }
      ],
      "title": "Current Sensor Ranking",
      "type": "barchart"
    }
  ],
  "refresh": "5m",
  "schemaVersion": 40,
  "tags": ["acm", "behavior", "health", "anomaly"],
  "templating": {
    "list": [
      {
        "current": {},
        "hide": 0,
        "includeAll": false,
        "label": "Datasource",
        "multi": false,
        "name": "datasource",
        "options": [],
        "query": "mssql",
        "queryValue": "",
        "refresh": 1,
        "regex": "",
        "skipUrlSync": false,
        "type": "datasource"
      },
      {
        "current": {},
        "datasource": { "type": "mssql", "uid": "${datasource}" },
        "definition": "SELECT EquipID AS __value, CONCAT(EquipCode, ' - ', EquipName) AS __text FROM Equipment ORDER BY EquipCode",
        "hide": 0,
        "includeAll": false,
        "label": "Equipment",
        "multi": false,
        "name": "equipment",
        "options": [],
        "query": "SELECT EquipID AS __value, CONCAT(EquipCode, ' - ', EquipName) AS __text FROM Equipment ORDER BY EquipCode",
        "refresh": 1,
        "regex": "",
        "skipUrlSync": false,
        "sort": 0,
        "type": "query"
      }
    ]
  },
  "time": { "from": "now-5y", "to": "now" },
  "timepicker": {},
  "timezone": "browser",
  "version": 1,
  "weekStart": ""
}
