{
  "annotations": {
    "list": [
      {
        "builtIn": 1,
        "datasource": {
          "type": "grafana",
          "uid": "-- Grafana --"
        },
        "enable": true,
        "hide": true,
        "iconColor": "rgba(0, 211, 255, 1)",
        "name": "Annotations & Alerts",
        "type": "dashboard"
      },
      {
        "datasource": {
          "type": "mssql",
          "uid": "${datasource}"
        },
        "enable": true,
        "iconColor": "red",
        "name": "Critical Episodes",
        "rawQuery": "SELECT \n  peak_timestamp AS time,\n  dominant_sensor AS text,\n  CONCAT('Episode ', CAST(episode_id AS VARCHAR), ' - ', severity, ' (Z=', CAST(ROUND(peak_z,1) AS VARCHAR), ')') AS tags\nFROM ACM_EpisodeDiagnostics\nWHERE EquipID = $equipment\n  AND severity IN ('MEDIUM', 'HIGH')\n  AND peak_timestamp BETWEEN $__timeFrom() AND $__timeTo()"
      }
    ]
  },
  "description": "Operator Dashboard - Real-time equipment health monitoring with interactive drill-downs",
  "editable": true,
  "fiscalYearStartMonth": 0,
  "graphTooltip": 1,
  "id": null,
  "links": [],
  "panels": [
    {
      "collapsed": false,
      "gridPos": {
        "h": 1,
        "w": 24,
        "x": 0,
        "y": 0
      },
      "id": 100,
      "panels": [],
      "title": "âš¡ EQUIPMENT STATUS - Quick Health Check",
      "type": "row"
    },
    {
      "datasource": {
        "type": "mssql",
        "uid": "${datasource}"
      },
      "fieldConfig": {
        "defaults": {
          "color": {
            "mode": "thresholds"
          },
          "mappings": [],
          "thresholds": {
            "mode": "absolute",
            "steps": [
              {
                "color": "dark-red",
                "value": null
              },
              {
                "color": "dark-orange",
                "value": 30
              },
              {
                "color": "yellow",
                "value": 60
              },
              {
                "color": "green",
                "value": 80
              }
            ]
          },
          "unit": "percent"
        }
      },
      "gridPos": {
        "h": 8,
        "w": 6,
        "x": 0,
        "y": 1
      },
      "id": 1,
      "options": {
        "colorMode": "background",
        "graphMode": "area",
        "justifyMode": "center",
        "orientation": "vertical",
        "reduceOptions": {
          "calcs": [
            "lastNotNull"
          ],
          "fields": "",
          "values": false
        },
        "showPercentChange": true,
        "text": {
          "titleSize": 18,
          "valueSize": 60
        },
        "textMode": "value_and_name"
      },
      "pluginVersion": "11.0.0",
      "targets": [
        {
          "datasource": {
            "type": "mssql",
            "uid": "${datasource}"
          },
          "format": "table",
          "rawQuery": true,
          "rawSql": "SELECT TOP 1 \n  ROUND(HealthIndex, 0) AS 'Health Score'\nFROM ACM_HealthTimeline \nWHERE EquipID = $equipment\nORDER BY Timestamp DESC",
          "refId": "A"
        }
      ],
      "title": "Current Health",
      "type": "stat"
    },
    {
      "datasource": {
        "type": "mssql",
        "uid": "${datasource}"
      },
      "fieldConfig": {
        "defaults": {
          "color": {
            "mode": "thresholds"
          },
          "mappings": [
            {
              "options": {
                "0": {
                  "color": "blue",
                  "text": "IDLE"
                },
                "1": {
                  "color": "green",
                  "text": "NORMAL"
                },
                "2": {
                  "color": "orange",
                  "text": "HIGH LOAD"
                }
              },
              "type": "value"
            }
          ],
          "thresholds": {
            "mode": "absolute",
            "steps": [
              {
                "color": "blue",
                "value": null
              }
            ]
          }
        }
      },
      "gridPos": {
        "h": 4,
        "w": 6,
        "x": 6,
        "y": 1
      },
      "id": 2,
      "options": {
        "colorMode": "background",
        "graphMode": "none",
        "justifyMode": "center",
        "orientation": "vertical",
        "reduceOptions": {
          "calcs": [
            "lastNotNull"
          ],
          "fields": "",
          "values": false
        },
        "text": {
          "titleSize": 14,
          "valueSize": 36
        },
        "textMode": "value_and_name"
      },
      "pluginVersion": "11.0.0",
      "targets": [
        {
          "datasource": {
            "type": "mssql",
            "uid": "${datasource}"
          },
          "format": "table",
          "rawQuery": true,
          "rawSql": "SELECT TOP 1 RegimeLabel AS 'Operating Mode'\nFROM ACM_RegimeTimeline\nWHERE EquipID = $equipment\nORDER BY Timestamp DESC",
          "refId": "A"
        }
      ],
      "title": "Operating Mode",
      "type": "stat"
    },
    {
      "datasource": {
        "type": "mssql",
        "uid": "${datasource}"
      },
      "fieldConfig": {
        "defaults": {
          "color": {
            "mode": "thresholds"
          },
          "mappings": [],
          "thresholds": {
            "mode": "absolute",
            "steps": [
              {
                "color": "green",
                "value": null
              },
              {
                "color": "yellow",
                "value": 5
              },
              {
                "color": "red",
                "value": 10
              }
            ]
          },
          "unit": "short"
        }
      },
      "gridPos": {
        "h": 4,
        "w": 6,
        "x": 12,
        "y": 1
      },
      "id": 3,
      "options": {
        "colorMode": "background",
        "graphMode": "area",
        "justifyMode": "center",
        "orientation": "vertical",
        "reduceOptions": {
          "calcs": [
            "sum"
          ],
          "fields": "",
          "values": false
        },
        "text": {
          "titleSize": 14,
          "valueSize": 36
        },
        "textMode": "value_and_name"
      },
      "pluginVersion": "11.0.0",
      "targets": [
        {
          "datasource": {
            "type": "mssql",
            "uid": "${datasource}"
          },
          "format": "table",
          "rawQuery": true,
          "rawSql": "SELECT COUNT(*) AS 'Active Defects'\nFROM ACM_SensorDefects\nWHERE EquipID = $equipment\n  AND ActiveDefect = '1'",
          "refId": "A"
        }
      ],
      "title": "Active Defects",
      "type": "stat"
    },
    {
      "datasource": {
        "type": "mssql",
        "uid": "${datasource}"
      },
      "fieldConfig": {
        "defaults": {
          "color": {
            "mode": "thresholds"
          },
          "mappings": [],
          "thresholds": {
            "mode": "absolute",
            "steps": [
              {
                "color": "green",
                "value": null
              },
              {
                "color": "yellow",
                "value": 3
              },
              {
                "color": "red",
                "value": 10
              }
            ]
          },
          "unit": "short"
        }
      },
      "gridPos": {
        "h": 4,
        "w": 6,
        "x": 18,
        "y": 1
      },
      "id": 4,
      "options": {
        "colorMode": "background",
        "graphMode": "area",
        "justifyMode": "center",
        "orientation": "vertical",
        "reduceOptions": {
          "calcs": [
            "sum"
          ],
          "fields": "",
          "values": false
        },
        "text": {
          "titleSize": 14,
          "valueSize": 36
        },
        "textMode": "value_and_name"
      },
      "pluginVersion": "11.0.0",
      "targets": [
        {
          "datasource": {
            "type": "mssql",
            "uid": "${datasource}"
          },
          "format": "table",
          "rawQuery": true,
          "rawSql": "SELECT COUNT(*) AS 'Recent Episodes'\nFROM ACM_Anomaly_Events\nWHERE EquipID = $equipment\n  AND StartTime >= DATEADD(day, -30, GETDATE())",
          "refId": "A"
        }
      ],
      "title": "Recent Episodes (30d)",
      "type": "stat"
    },
    {
      "datasource": {
        "type": "mssql",
        "uid": "${datasource}"
      },
      "description": "Top detectors showing abnormal behavior",
      "fieldConfig": {
        "defaults": {
          "color": {
            "mode": "thresholds"
          },
          "custom": {
            "align": "auto",
            "cellOptions": {
              "type": "auto"
            },
            "inspect": false
          },
          "mappings": [],
          "thresholds": {
            "mode": "absolute",
            "steps": [
              {
                "color": "green",
                "value": null
              }
            ]
          }
        },
        "overrides": [
          {
            "matcher": {
              "id": "byName",
              "options": "Current Z"
            },
            "properties": [
              {
                "id": "custom.cellOptions",
                "value": {
                  "type": "color-background"
                }
              },
              {
                "id": "thresholds",
                "value": {
                  "mode": "absolute",
                  "steps": [
                    {
                      "color": "green",
                      "value": null
                    },
                    {
                      "color": "yellow",
                      "value": 2
                    },
                    {
                      "color": "orange",
                      "value": 3
                    },
                    {
                      "color": "red",
                      "value": 5
                    }
                  ]
                }
              }
            ]
          },
          {
            "matcher": {
              "id": "byName",
              "options": "Active"
            },
            "properties": [
              {
                "id": "mappings",
                "value": [
                  {
                    "options": {
                      "0": {
                        "color": "green",
                        "text": "OK"
                      },
                      "1": {
                        "color": "red",
                        "text": "DEFECT"
                      }
                    },
                    "type": "value"
                  }
                ]
              },
              {
                "id": "custom.cellOptions",
                "value": {
                  "type": "color-background"
                }
              }
            ]
          }
        ]
      },
      "gridPos": {
        "h": 4,
        "w": 18,
        "x": 6,
        "y": 5
      },
      "id": 5,
      "options": {
        "cellHeight": "sm",
        "footer": {
          "countRows": false,
          "fields": "",
          "reducer": [
            "sum"
          ],
          "show": false
        },
        "showHeader": true,
        "sortBy": []
      },
      "pluginVersion": "11.0.0",
      "targets": [
        {
          "datasource": {
            "type": "mssql",
            "uid": "${datasource}"
          },
          "format": "table",
          "rawQuery": true,
          "rawSql": "SELECT TOP 10\n  DetectorType AS 'Detector',\n  ROUND(CurrentZ, 2) AS 'Current Z',\n  ROUND(MaxZ, 2) AS 'Peak Z',\n  CASE WHEN ActiveDefect = '1' THEN 1 ELSE 0 END AS 'Active',\n  Severity AS 'Severity'\nFROM ACM_SensorDefects\nWHERE EquipID = $equipment\nORDER BY ABS(CurrentZ) DESC",
          "refId": "A"
        }
      ],
      "title": "âš ï¸ What's Wrong Right Now?",
      "type": "table"
    },
    {
      "collapsed": false,
      "gridPos": {
        "h": 1,
        "w": 24,
        "x": 0,
        "y": 9
      },
      "id": 101,
      "panels": [],
      "title": "ðŸ“Š HEALTH TIMELINE - Equipment Performance Over Time",
      "type": "row"
    },
    {
      "datasource": {
        "type": "mssql",
        "uid": "${datasource}"
      },
      "description": "Health score with operating mode overlay. Episode annotations show critical events.",
      "fieldConfig": {
        "defaults": {
          "color": {
            "mode": "palette-classic"
          },
          "custom": {
            "axisBorderShow": false,
            "axisCenteredZero": false,
            "axisColorMode": "text",
            "axisLabel": "Health Score (%)",
            "axisPlacement": "auto",
            "barAlignment": 0,
            "drawStyle": "line",
            "fillOpacity": 20,
            "gradientMode": "scheme",
            "hideFrom": {
              "legend": false,
              "tooltip": false,
              "viz": false
            },
            "insertNulls": false,
            "lineInterpolation": "smooth",
            "lineWidth": 3,
            "pointSize": 5,
            "scaleDistribution": {
              "type": "linear"
            },
            "showPoints": "never",
            "spanNulls": 3600000,
            "stacking": {
              "group": "A",
              "mode": "none"
            },
            "thresholdsStyle": {
              "mode": "area"
            }
          },
          "mappings": [],
          "max": 100,
          "min": 0,
          "thresholds": {
            "mode": "absolute",
            "steps": [
              {
                "color": "dark-red",
                "value": null
              },
              {
                "color": "dark-orange",
                "value": 30
              },
              {
                "color": "yellow",
                "value": 60
              },
              {
                "color": "green",
                "value": 80
              }
            ]
          },
          "unit": "percent"
        },
        "overrides": [
          {
            "matcher": {
              "id": "byName",
              "options": "Health"
            },
            "properties": [
              {
                "id": "custom.fillOpacity",
                "value": 30
              },
              {
                "id": "color",
                "value": {
                  "fixedColor": "green",
                  "mode": "fixed"
                }
              }
            ]
          },
          {
            "matcher": {
              "id": "byName",
              "options": "Regime"
            },
            "properties": [
              {
                "id": "custom.lineWidth",
                "value": 0
              },
              {
                "id": "custom.fillOpacity",
                "value": 15
              },
              {
                "id": "custom.drawStyle",
                "value": "bars"
              },
              {
                "id": "custom.axisPlacement",
                "value": "hidden"
              },
              {
                "id": "color",
                "value": {
                  "fixedColor": "blue",
                  "mode": "fixed"
                }
              },
              {
                "id": "max",
                "value": 4
              }
            ]
          }
        ]
      },
      "gridPos": {
        "h": 10,
        "w": 24,
        "x": 0,
        "y": 10
      },
      "id": 10,
      "options": {
        "legend": {
          "calcs": [
            "mean",
            "min",
            "max",
            "lastNotNull"
          ],
          "displayMode": "table",
          "placement": "bottom",
          "showLegend": true
        },
        "tooltip": {
          "mode": "multi",
          "sort": "desc"
        }
      },
      "pluginVersion": "11.0.0",
      "targets": [
        {
          "datasource": {
            "type": "mssql",
            "uid": "${datasource}"
          },
          "format": "time_series",
          "rawQuery": true,
          "rawSql": "SELECT \n  Timestamp AS time,\n  HealthIndex AS value,\n  'Health' AS metric\nFROM ACM_HealthTimeline\nWHERE EquipID = $equipment\n  AND Timestamp BETWEEN $__timeFrom() AND $__timeTo()\nUNION ALL\nSELECT \n  Timestamp AS time,\n  RegimeLabel * 25 AS value,\n  'Regime' AS metric\nFROM ACM_RegimeTimeline\nWHERE EquipID = $equipment\n  AND Timestamp BETWEEN $__timeFrom() AND $__timeTo()\nORDER BY time ASC",
          "refId": "A"
        }
      ],
      "title": "Health + Operating Mode (Bars = regime background)",
      "type": "timeseries"
    },
    {
      "collapsed": false,
      "gridPos": {
        "h": 1,
        "w": 24,
        "x": 0,
        "y": 20
      },
      "id": 102,
      "panels": [],
      "title": "ðŸ” DETECTOR SCORES - Multi-Detector View",
      "type": "row"
    },
    {
      "datasource": {
        "type": "mssql",
        "uid": "${datasource}"
      },
      "description": "All detector Z-scores over time. Hover to see which detectors spiked when.",
      "fieldConfig": {
        "defaults": {
          "color": {
            "mode": "palette-classic"
          },
          "custom": {
            "axisBorderShow": false,
            "axisCenteredZero": true,
            "axisColorMode": "text",
            "axisLabel": "Z-Score",
            "axisPlacement": "auto",
            "barAlignment": 0,
            "drawStyle": "line",
            "fillOpacity": 10,
            "gradientMode": "none",
            "hideFrom": {
              "legend": false,
              "tooltip": false,
              "viz": false
            },
            "insertNulls": false,
            "lineInterpolation": "smooth",
            "lineWidth": 2,
            "pointSize": 5,
            "scaleDistribution": {
              "type": "linear"
            },
            "showPoints": "never",
            "spanNulls": 3600000,
            "stacking": {
              "group": "A",
              "mode": "none"
            },
            "thresholdsStyle": {
              "mode": "line+area"
            }
          },
          "mappings": [],
          "thresholds": {
            "mode": "absolute",
            "steps": [
              {
                "color": "transparent",
                "value": null
              },
              {
                "color": "red",
                "value": 3
              }
            ]
          }
        }
      },
      "gridPos": {
        "h": 10,
        "w": 24,
        "x": 0,
        "y": 21
      },
      "id": 20,
      "options": {
        "legend": {
          "calcs": [
            "max",
            "mean"
          ],
          "displayMode": "table",
          "placement": "right",
          "showLegend": true
        },
        "tooltip": {
          "mode": "multi",
          "sort": "desc"
        }
      },
      "pluginVersion": "11.0.0",
      "targets": [
        {
          "datasource": {
            "type": "mssql",
            "uid": "${datasource}"
          },
          "format": "time_series",
          "rawQuery": true,
          "rawSql": "SELECT \n  Timestamp AS time,\n  pca_spe_z AS value,\n  'PCA-SPE' AS metric\nFROM ACM_Scores_Wide\nWHERE EquipID = $equipment\n  AND Timestamp BETWEEN $__timeFrom() AND $__timeTo()\nUNION ALL\nSELECT \n  Timestamp AS time,\n  pca_t2_z AS value,\n  'PCA-T2' AS metric\nFROM ACM_Scores_Wide\nWHERE EquipID = $equipment\n  AND Timestamp BETWEEN $__timeFrom() AND $__timeTo()\nUNION ALL\nSELECT \n  Timestamp AS time,\n  FusedZ AS value,\n  'Fused Score' AS metric\nFROM ACM_HealthTimeline\nWHERE EquipID = $equipment\n  AND Timestamp BETWEEN $__timeFrom() AND $__timeTo()\nORDER BY time ASC",
          "refId": "A"
        }
      ],
      "title": "Multi-Detector Z-Scores Timeline",
      "type": "timeseries"
    },
    {
      "collapsed": false,
      "gridPos": {
        "h": 1,
        "w": 24,
        "x": 0,
        "y": 31
      },
      "id": 103,
      "panels": [],
      "title": "ðŸ”¥ EPISODE INVESTIGATION - Anomaly Events Deep Dive",
      "type": "row"
    },
    {
      "datasource": {
        "type": "mssql",
        "uid": "${datasource}"
      },
      "description": "Click any row to see detailed episode forensics",
      "fieldConfig": {
        "defaults": {
          "color": {
            "mode": "thresholds"
          },
          "custom": {
            "align": "auto",
            "cellOptions": {
              "type": "auto"
            },
            "inspect": false
          },
          "mappings": [],
          "thresholds": {
            "mode": "absolute",
            "steps": [
              {
                "color": "green",
                "value": null
              }
            ]
          }
        },
        "overrides": [
          {
            "matcher": {
              "id": "byName",
              "options": "Severity"
            },
            "properties": [
              {
                "id": "mappings",
                "value": [
                  {
                    "options": {
                      "HIGH": {
                        "color": "dark-red",
                        "text": "HIGH"
                      },
                      "MEDIUM": {
                        "color": "dark-orange",
                        "text": "MEDIUM"
                      },
                      "LOW": {
                        "color": "dark-yellow",
                        "text": "LOW"
                      }
                    },
                    "type": "value"
                  }
                ]
              },
              {
                "id": "custom.cellOptions",
                "value": {
                  "type": "color-background"
                }
              }
            ]
          },
          {
            "matcher": {
              "id": "byName",
              "options": "Peak Z"
            },
            "properties": [
              {
                "id": "custom.cellOptions",
                "value": {
                  "type": "gauge"
                }
              },
              {
                "id": "max",
                "value": 10
              },
              {
                "id": "min",
                "value": 0
              },
              {
                "id": "thresholds",
                "value": {
                  "mode": "absolute",
                  "steps": [
                    {
                      "color": "green",
                      "value": null
                    },
                    {
                      "color": "yellow",
                      "value": 2
                    },
                    {
                      "color": "orange",
                      "value": 3
                    },
                    {
                      "color": "red",
                      "value": 5
                    }
                  ]
                }
              }
            ]
          }
        ]
      },
      "gridPos": {
        "h": 10,
        "w": 24,
        "x": 0,
        "y": 32
      },
      "id": 30,
      "options": {
        "cellHeight": "sm",
        "footer": {
          "countRows": false,
          "fields": "",
          "reducer": [
            "sum"
          ],
          "show": false
        },
        "showHeader": true,
        "sortBy": [
          {
            "desc": true,
            "displayName": "When"
          }
        ]
      },
      "pluginVersion": "11.0.0",
      "targets": [
        {
          "datasource": {
            "type": "mssql",
            "uid": "${datasource}"
          },
          "format": "table",
          "rawQuery": true,
          "rawSql": "SELECT \n  ed.episode_id AS 'Episode',\n  FORMAT(ed.peak_timestamp, 'yyyy-MM-dd HH:mm') AS 'When',\n  ed.severity AS 'Severity',\n  ROUND(ed.peak_z, 2) AS 'Peak Z',\n  ROUND(ed.duration_h, 1) AS 'Duration (h)',\n  ed.dominant_sensor AS 'Root Cause Detector',\n  ROUND(ed.min_health_index, 0) AS 'Min Health',\n  ed.severity_reason AS 'Reason'\nFROM ACM_EpisodeDiagnostics ed\nWHERE ed.EquipID = $equipment\n  AND ed.peak_timestamp BETWEEN $__timeFrom() AND $__timeTo()\nORDER BY ed.peak_timestamp DESC",
          "refId": "A"
        }
      ],
      "title": "Episode Timeline (Recent Anomalies)",
      "type": "table"
    },
    {
      "datasource": {
        "type": "mssql",
        "uid": "${datasource}"
      },
      "description": "Which sensors contributed to each episode",
      "fieldConfig": {
        "defaults": {
          "color": {
            "mode": "palette-classic"
          },
          "custom": {
            "axisBorderShow": false,
            "axisCenteredZero": false,
            "axisColorMode": "text",
            "axisLabel": "Contribution Score",
            "axisPlacement": "auto",
            "fillOpacity": 80,
            "gradientMode": "hue",
            "hideFrom": {
              "legend": false,
              "tooltip": false,
              "viz": false
            },
            "lineWidth": 1,
            "scaleDistribution": {
              "type": "linear"
            },
            "thresholdsStyle": {
              "mode": "off"
            }
          },
          "mappings": [],
          "thresholds": {
            "mode": "absolute",
            "steps": [
              {
                "color": "green",
                "value": null
              }
            ]
          }
        }
      },
      "gridPos": {
        "h": 8,
        "w": 12,
        "x": 0,
        "y": 42
      },
      "id": 31,
      "options": {
        "barRadius": 0,
        "barWidth": 0.8,
        "fullHighlight": false,
        "groupWidth": 0.7,
        "legend": {
          "calcs": [],
          "displayMode": "list",
          "placement": "bottom",
          "showLegend": false
        },
        "orientation": "horizontal",
        "showValue": "always",
        "stacking": "none",
        "tooltip": {
          "mode": "single",
          "sort": "none"
        },
        "xTickLabelRotation": 0,
        "xTickLabelSpacing": 0
      },
      "pluginVersion": "11.0.0",
      "targets": [
        {
          "datasource": {
            "type": "mssql",
            "uid": "${datasource}"
          },
          "format": "table",
          "rawQuery": true,
          "rawSql": "SELECT TOP 10\n  DetectorType AS Sensor,\n  ROUND(MaxZ, 2) AS Score\nFROM ACM_SensorDefects\nWHERE EquipID = $equipment\nORDER BY MaxZ DESC",
          "refId": "A"
        }
      ],
      "title": "Top Defective Sensors (by Peak Z-Score)",
      "type": "barchart"
    },
    {
      "datasource": {
        "type": "mssql",
        "uid": "${datasource}"
      },
      "description": "Distribution of detector types by severity",
      "fieldConfig": {
        "defaults": {
          "color": {
            "mode": "palette-classic"
          },
          "custom": {
            "hideFrom": {
              "legend": false,
              "tooltip": false,
              "viz": false
            }
          },
          "mappings": []
        }
      },
      "gridPos": {
        "h": 8,
        "w": 12,
        "x": 12,
        "y": 42
      },
      "id": 32,
      "options": {
        "displayLabels": [
          "percent"
        ],
        "legend": {
          "calcs": [],
          "displayMode": "table",
          "placement": "right",
          "showLegend": true,
          "values": [
            "value"
          ]
        },
        "pieType": "donut",
        "reduceOptions": {
          "calcs": [
            "lastNotNull"
          ],
          "fields": "",
          "values": false
        },
        "tooltip": {
          "mode": "single",
          "sort": "none"
        }
      },
      "pluginVersion": "11.0.0",
      "targets": [
        {
          "datasource": {
            "type": "mssql",
            "uid": "${datasource}"
          },
          "format": "table",
          "rawQuery": true,
          "rawSql": "SELECT \n  Severity AS 'Severity Level',\n  COUNT(*) AS 'Count'\nFROM ACM_SensorDefects\nWHERE EquipID = $equipment\nGROUP BY Severity",
          "refId": "A"
        }
      ],
      "title": "Defect Distribution by Severity",
      "type": "piechart"
    },
    {
      "collapsed": false,
      "gridPos": {
        "h": 1,
        "w": 24,
        "x": 0,
        "y": 50
      },
      "id": 104,
      "panels": [],
      "title": "ðŸŽ¯ REGIME ANALYSIS - Operating Mode Patterns",
      "type": "row"
    },
    {
      "datasource": {
        "type": "mssql",
        "uid": "${datasource}"
      },
      "description": "Time spent in each operating regime",
      "fieldConfig": {
        "defaults": {
          "color": {
            "mode": "palette-classic"
          },
          "custom": {
            "axisBorderShow": false,
            "axisCenteredZero": false,
            "axisColorMode": "text",
            "axisLabel": "Hours",
            "axisPlacement": "auto",
            "fillOpacity": 80,
            "gradientMode": "scheme",
            "hideFrom": {
              "legend": false,
              "tooltip": false,
              "viz": false
            },
            "lineWidth": 1,
            "scaleDistribution": {
              "type": "linear"
            },
            "thresholdsStyle": {
              "mode": "off"
            }
          },
          "mappings": [
            {
              "options": {
                "0": {
                  "color": "blue",
                  "text": "IDLE"
                },
                "1": {
                  "color": "green",
                  "text": "NORMAL"
                },
                "2": {
                  "color": "orange",
                  "text": "HIGH LOAD"
                }
              },
              "type": "value"
            }
          ],
          "thresholds": {
            "mode": "absolute",
            "steps": [
              {
                "color": "green",
                "value": null
              }
            ]
          },
          "unit": "h"
        }
      },
      "gridPos": {
        "h": 8,
        "w": 12,
        "x": 0,
        "y": 51
      },
      "id": 40,
      "options": {
        "barRadius": 0.1,
        "barWidth": 0.8,
        "fullHighlight": false,
        "groupWidth": 0.7,
        "legend": {
          "calcs": [],
          "displayMode": "list",
          "placement": "bottom",
          "showLegend": false
        },
        "orientation": "horizontal",
        "showValue": "always",
        "stacking": "none",
        "tooltip": {
          "mode": "single",
          "sort": "none"
        },
        "xTickLabelRotation": 0,
        "xTickLabelSpacing": 0
      },
      "pluginVersion": "11.0.0",
      "targets": [
        {
          "datasource": {
            "type": "mssql",
            "uid": "${datasource}"
          },
          "format": "table",
          "rawQuery": true,
          "rawSql": "SELECT \n  RegimeLabel AS Regime,\n  TotalHours AS Hours\nFROM ACM_RegimeOccupancy\nWHERE EquipID = $equipment\nORDER BY RegimeLabel",
          "refId": "A"
        }
      ],
      "title": "Regime Occupancy (Time in Each Mode)",
      "type": "barchart"
    },
    {
      "datasource": {
        "type": "mssql",
        "uid": "${datasource}"
      },
      "description": "Regime transitions over time",
      "fieldConfig": {
        "defaults": {
          "color": {
            "mode": "palette-classic"
          },
          "custom": {
            "axisBorderShow": false,
            "axisCenteredZero": false,
            "axisColorMode": "text",
            "axisLabel": "Regime",
            "axisPlacement": "auto",
            "barAlignment": 0,
            "drawStyle": "line",
            "fillOpacity": 20,
            "gradientMode": "scheme",
            "hideFrom": {
              "legend": false,
              "tooltip": false,
              "viz": false
            },
            "insertNulls": false,
            "lineInterpolation": "stepAfter",
            "lineWidth": 3,
            "pointSize": 5,
            "scaleDistribution": {
              "type": "linear"
            },
            "showPoints": "never",
            "spanNulls": false,
            "stacking": {
              "group": "A",
              "mode": "none"
            },
            "thresholdsStyle": {
              "mode": "off"
            }
          },
          "mappings": [
            {
              "options": {
                "0": {
                  "color": "blue",
                  "text": "IDLE"
                },
                "1": {
                  "color": "green",
                  "text": "NORMAL"
                },
                "2": {
                  "color": "orange",
                  "text": "HIGH LOAD"
                }
              },
              "type": "value"
            }
          ],
          "max": 3,
          "min": 0,
          "thresholds": {
            "mode": "absolute",
            "steps": [
              {
                "color": "green",
                "value": null
              }
            ]
          }
        }
      },
      "gridPos": {
        "h": 8,
        "w": 12,
        "x": 12,
        "y": 51
      },
      "id": 41,
      "options": {
        "legend": {
          "calcs": [],
          "displayMode": "list",
          "placement": "bottom",
          "showLegend": true
        },
        "tooltip": {
          "mode": "single",
          "sort": "none"
        }
      },
      "pluginVersion": "11.0.0",
      "targets": [
        {
          "datasource": {
            "type": "mssql",
            "uid": "${datasource}"
          },
          "format": "time_series",
          "rawQuery": true,
          "rawSql": "SELECT \n  Timestamp AS time,\n  RegimeLabel AS value,\n  'Operating Mode' AS metric\nFROM ACM_RegimeTimeline\nWHERE EquipID = $equipment\n  AND Timestamp BETWEEN $__timeFrom() AND $__timeTo()\nORDER BY Timestamp ASC",
          "refId": "A"
        }
      ],
      "title": "Regime Timeline (Mode Changes Over Time)",
      "type": "timeseries"
    },
    {
      "collapsed": false,
      "gridPos": {
        "h": 1,
        "w": 24,
        "x": 0,
        "y": 59
      },
      "id": 105,
      "panels": [],
      "title": "ðŸ”® SENSOR HEATMAP - Intensity View",
      "type": "row"
    },
    {
      "datasource": {
        "type": "mssql",
        "uid": "${datasource}"
      },
      "description": "Heatmap showing OMR sensor contribution intensity. Darker = bigger deviation.",
      "fieldConfig": {
        "defaults": {
          "custom": {
            "hideFrom": {
              "legend": false,
              "tooltip": false,
              "viz": false
            },
            "scaleDistribution": {
              "type": "linear"
            }
          }
        }
      },
      "gridPos": {
        "h": 10,
        "w": 24,
        "x": 0,
        "y": 60
      },
      "id": 50,
      "options": {
        "calculate": false,
        "cellGap": 2,
        "cellValues": {},
        "color": {
          "exponent": 0.5,
          "fill": "dark-red",
          "mode": "scheme",
          "reverse": false,
          "scale": "exponential",
          "scheme": "Oranges",
          "steps": 128
        },
        "exemplars": {
          "color": "rgba(255,0,255,0.7)"
        },
        "filterValues": {
          "le": 1e-9
        },
        "legend": {
          "show": true
        },
        "rowsFrame": {
          "layout": "auto"
        },
        "tooltip": {
          "mode": "single",
          "showColorScale": false,
          "yHistogram": false
        },
        "yAxis": {
          "axisPlacement": "left",
          "reverse": false
        }
      },
      "pluginVersion": "11.0.0",
      "targets": [
        {
          "datasource": {
            "type": "mssql",
            "uid": "${datasource}"
          },
          "format": "time_series",
          "rawQuery": true,
          "rawSql": "SELECT \n  Timestamp AS time,\n  ABS(Contribution) AS value,\n  SensorName AS metric\nFROM ACM_OMRContributionsLong\nWHERE EquipID = $equipment\n  AND Timestamp BETWEEN $__timeFrom() AND $__timeTo()\n  AND ABS(Contribution) > 0.05\nORDER BY Timestamp ASC",
          "refId": "A"
        }
      ],
      "title": "OMR Sensor Contributions Heatmap",
      "type": "heatmap"
    }
  ],
  "refresh": "",
  "schemaVersion": 39,
  "tags": [
    "acm",
    "operator-dashboard",
    "anomaly-detection"
  ],
  "templating": {
    "list": [
      {
        "current": {
          "selected": false,
          "text": "MSSQL - ACM",
          "value": "MSSQL - ACM"
        },
        "hide": 0,
        "includeAll": false,
        "multi": false,
        "name": "datasource",
        "options": [],
        "query": "mssql",
        "queryValue": "",
        "refresh": 1,
        "regex": "",
        "skipUrlSync": false,
        "type": "datasource"
      },
      {
        "current": {
          "selected": false,
          "text": "1",
          "value": "1"
        },
        "datasource": {
          "type": "mssql",
          "uid": "${datasource}"
        },
        "definition": "SELECT CAST(EquipID AS VARCHAR) AS __value, COALESCE(EquipName, CONCAT('Equipment-', CAST(EquipID AS VARCHAR))) AS __text FROM Equipment ORDER BY EquipID",
        "hide": 0,
        "includeAll": false,
        "multi": false,
        "name": "equipment",
        "options": [],
        "query": "SELECT CAST(EquipID AS VARCHAR) AS __value, COALESCE(EquipName, CONCAT('Equipment-', CAST(EquipID AS VARCHAR))) AS __text FROM Equipment ORDER BY EquipID",
        "refresh": 1,
        "regex": "",
        "skipUrlSync": false,
        "sort": 0,
        "type": "query"
      }
    ]
  },
  "time": {
    "from": "now-90d",
    "to": "now"
  },
  "timepicker": {},
  "timezone": "browser",
  "title": "ACM Operator Dashboard v3 - FIXED",
  "uid": "acm-operator-v3-fixed",
  "version": 1,
  "weekStart": ""
}
